vsdpir/__init__.py
vsdpir/__main__.py
vsdpir/basicblock.py
vsdpir/network_unet.py
vsdpir-4.3.0.dist-info/METADATA
vsdpir-4.3.0.dist-info/WHEEL
vsdpir-4.3.0.dist-info/licenses/LICENSE
vsdpir-4.3.0.dist-info/RECORD
