Metadata-Version: 2.4
Name: vsdpir
Version: 4.3.0
Summary: DPIR function for VapourSynth
Project-URL: Homepage, https://github.com/HolyWu/vs-dpir
Project-URL: Issues, https://github.com/HolyWu/vs-dpir/issues
Author-email: HolyWu <holywu@gmail.com>
License-File: LICENSE
Keywords: DPIR,PyTorch,TensorRT,VapourSynth
Classifier: Environment :: GPU :: NVIDIA CUDA
Classifier: License :: OSI Approved :: MIT License
Classifier: Operating System :: OS Independent
Classifier: Programming Language :: Python :: 3
Classifier: Topic :: Multimedia :: Video
Requires-Python: >=3.10
Requires-Dist: numpy
Requires-Dist: requests
Requires-Dist: torch>=2.6.0
Requires-Dist: tqdm
Requires-Dist: vapoursynth>=66
